{
	"name": "DS_ABLB_Input",
	"properties": {
		"linkedServiceName": {
			"referenceName": "LS_ABLB_Input",
			"type": "LinkedServiceReference"
		},
		"folder": {
			"name": "MODULE 2"
		},
		"annotations": [],
		"type": "DelimitedText",
		"typeProperties": {
			"location": {
				"type": "AzureBlobStorageLocation",
				"container": "movies"
			},
			"columnDelimiter": ",",
			"rowDelimiter": "\n",
			"escapeChar": "\"",
			"firstRowAsHeader": true,
			"quoteChar": "\""
		},
		"schema": [
			{
				"name": "cast",
				"type": "String"
			},
			{
				"name": "crew",
				"type": "String"
			},
			{
				"name": "id",
				"type": "String"
			}
		]
	},
	"type": "Microsoft.DataFactory/factories/datasets"
}